{
  "main": {
    "id": "071f79513671f2a7",
    "type": "split",
    "children": [
      {
        "id": "a24ed533477ef7db",
        "type": "tabs",
        "children": [
          {
            "id": "d813eede77768419",
            "type": "leaf",
            "state": {
              "type": "release-notes",
              "state": {
                "currentVersion": "1.10.6"
              },
              "icon": "lucide-book-up",
              "title": "примечания к выпуску 1.10.6"
            }
          },
          {
            "id": "3f998e12bdb2727c",
            "type": "leaf",
            "state": {
              "type": "markdown",
              "state": {
                "file": "02.12.2025 - Тестирование UI.md",
                "mode": "source",
                "source": false
              },
              "icon": "lucide-file",
              "title": "02.12.2025 - Тестирование UI"
            }
          }
        ],
        "currentTab": 1
      }
    ],
    "direction": "vertical"
  },
  "left": {
    "id": "51045c368ab325c4",
    "type": "split",
    "children": [
      {
        "id": "40df0b9b1ebc379f",
        "type": "tabs",
        "children": [
          {
            "id": "745c0e8865583f19",
            "type": "leaf",
            "state": {
              "type": "file-explorer",
              "state": {
                "sortOrder": "alphabetical",
                "autoReveal": false
              },
              "icon": "lucide-folder-closed",
              "title": "Файловый менеджер"
            }
          },
          {
            "id": "21051665f70c8b98",
            "type": "leaf",
            "state": {
              "type": "search",
              "state": {
                "query": "",
                "matchingCase": false,
                "explainSearch": false,
                "collapseAll": false,
                "extraContext": false,
                "sortOrder": "alphabetical"
              },
              "icon": "lucide-search",
              "title": "Поиск"
            }
          },
          {
            "id": "6fe75170b079466e",
            "type": "leaf",
            "state": {
              "type": "bookmarks",
              "state": {},
              "icon": "lucide-bookmark",
              "title": "Закладки"
            }
          }
        ]
      }
    ],
    "direction": "horizontal",
    "width": 300
  },
  "right": {
    "id": "bb3a9066b7f5fd76",
    "type": "split",
    "children": [
      {
        "id": "a3771fe3ab1b4e58",
        "type": "tabs",
        "children": [
          {
            "id": "f1a4e13de71b2248",
            "type": "leaf",
            "state": {
              "type": "backlink",
              "state": {
                "file": "02.12.2025 - Тестирование UI.md",
                "collapseAll": false,
                "extraContext": false,
                "sortOrder": "alphabetical",
                "showSearch": false,
                "searchQuery": "",
                "backlinkCollapsed": false,
                "unlinkedCollapsed": true
              },
              "icon": "links-coming-in",
              "title": "Обратные ссылки для 02.12.2025 - Тестирование UI"
            }
          },
          {
            "id": "e200d360ccc2893d",
            "type": "leaf",
            "state": {
              "type": "outgoing-link",
              "state": {
                "file": "02.12.2025 - Тестирование UI.md",
                "linksCollapsed": false,
                "unlinkedCollapsed": true
              },
              "icon": "links-going-out",
              "title": "Исходящие ссылки из 02.12.2025 - Тестирование UI"
            }
          },
          {
            "id": "ce34b8371e3efa45",
            "type": "leaf",
            "state": {
              "type": "tag",
              "state": {
                "sortOrder": "frequency",
                "useHierarchy": true,
                "showSearch": false,
                "searchQuery": ""
              },
              "icon": "lucide-tags",
              "title": "Теги"
            }
          },
          {
            "id": "6cd289b9129010d2",
            "type": "leaf",
            "state": {
              "type": "all-properties",
              "state": {
                "sortOrder": "frequency",
                "showSearch": false,
                "searchQuery": ""
              },
              "icon": "lucide-archive",
              "title": "Все свойства"
            }
          },
          {
            "id": "e4e9336240005b25",
            "type": "leaf",
            "state": {
              "type": "outline",
              "state": {
                "file": "02.12.2025 - Тестирование UI.md",
                "followCursor": false,
                "showSearch": false,
                "searchQuery": ""
              },
              "icon": "lucide-list",
              "title": "Структура 02.12.2025 - Тестирование UI"
            }
          }
        ]
      }
    ],
    "direction": "horizontal",
    "width": 300,
    "collapsed": true
  },
  "left-ribbon": {
    "hiddenItems": {
      "switcher:Меню быстрого перехода": false,
      "graph:Граф": false,
      "canvas:Создать новый холст": false,
      "daily-notes:Сегодняшняя заметка": false,
      "templates:Вставить шаблон": false,
      "command-palette:Открыть палитру команд": false,
      "bases:Создать новую базу": false
    }
  },
  "active": "3f998e12bdb2727c",
  "lastOpenFiles": [
    "Pasted image 20251202133934.png",
    "Pasted image 20251202133834.png",
    "02.12.2025 - Тестирование UI.md"
  ]
}